computer_server/__init__.py
computer_server/__main__.py
computer_server/browser.py
computer_server/cli.py
computer_server/diorama/__init__.py
computer_server/diorama/base.py
computer_server/diorama/diorama.py
computer_server/diorama/diorama_computer.py
computer_server/diorama/draw.py
computer_server/diorama/macos.py
computer_server/diorama/safezone.py
computer_server/handlers/android.py
computer_server/handlers/base.py
computer_server/handlers/factory.py
computer_server/handlers/generic.py
computer_server/handlers/linux.py
computer_server/handlers/macos.py
computer_server/handlers/windows.py
computer_server/main.py
computer_server/mcp_server.py
computer_server/server.py
computer_server/utils/__init__.py
computer_server/utils/helpers.py
computer_server/utils/wallpaper.py
computer_server/watchdog.py
cua_computer_server-0.3.16.dist-info/METADATA
cua_computer_server-0.3.16.dist-info/WHEEL
cua_computer_server-0.3.16.dist-info/entry_points.txt
cua_computer_server-0.3.16.dist-info/RECORD
