Metadata-Version: 2.1
Name: cua-computer-server
Version: 0.3.16
Summary: Server component for the Computer-Use Interface (CUI) framework powering Cua
Author-Email: TryCua <gh@trycua.com>
License: MIT
Project-URL: homepage, https://github.com/trycua/cua
Project-URL: repository, https://github.com/trycua/cua
Requires-Python: <3.14,>=3.12
Requires-Dist: fastapi>=0.111.0
Requires-Dist: uvicorn[standard]>=0.27.0
Requires-Dist: pydantic>=2.0.0
Requires-Dist: pynput>=1.8.1
Requires-Dist: pillow>=10.2.0
Requires-Dist: aiohttp>=3.9.1
Requires-Dist: pyperclip>=1.9.0
Requires-Dist: websockets>=12.0
Requires-Dist: pywinctl>=0.4.1
Requires-Dist: playwright>=1.40.0
Requires-Dist: fastmcp<3,>=2.0
Requires-Dist: pyobjc-framework-Cocoa>=10.1; sys_platform == "darwin"
Requires-Dist: pyobjc-framework-Quartz>=10.1; sys_platform == "darwin"
Requires-Dist: pyobjc-framework-ApplicationServices>=10.1; sys_platform == "darwin"
Requires-Dist: python-xlib>=0.33; sys_platform == "linux"
Requires-Dist: pywin32>=310; sys_platform == "win32"
Requires-Dist: python-certifi-win32; sys_platform == "win32"
Requires-Dist: cua-core
Provides-Extra: macos
Requires-Dist: pyobjc-framework-Cocoa>=10.1; extra == "macos"
Requires-Dist: pyobjc-framework-Quartz>=10.1; extra == "macos"
Requires-Dist: pyobjc-framework-ApplicationServices>=10.1; extra == "macos"
Provides-Extra: linux
Requires-Dist: python-xlib>=0.33; extra == "linux"
Provides-Extra: windows
Requires-Dist: pywin32>=310; extra == "windows"
